{
  "id": "FID-0035",
  "title": "Zero struct-layout static asserts for N64-layout ROM structs (StandTile, PROPDEF records); protection is compiler flags only",
  "class": "instrumentation-gap",
  "surface": "infra",
  "priority": "P1",
  "status": "verified",
  "suspect": [
    "src/bondtypes.h:387-449",
    "CMakeLists.txt:708-723"
  ],
  "repro": "",
  "evidence": [
    {
      "kind": "doc-anchor",
      "path": "docs/design/FAITHFULNESS_S_TIER_PLAN.md#0.3",
      "note": "seed from FAITHFULNESS_S_TIER_PLAN \u00a70.3"
    },
    {
      "kind": "gate-log",
      "path": "docs/fidelity/reports/struct_layout_verify.log"
    }
  ],
  "history": [
    {
      "ts": "2026-07-09T00:00:00Z",
      "from": "",
      "to": "root-caused",
      "evidence": "docs/design/FAITHFULNESS_S_TIER_PLAN.md#0.3",
      "note": "seed from FAITHFULNESS_S_TIER_PLAN \u00a70.3"
    },
    {
      "ts": "2026-07-09T21:20:39Z",
      "from": "root-caused",
      "to": "verified",
      "evidence": "docs/fidelity/reports/struct_layout_verify.log",
      "note": "struct_layout ctest PASS (macOS clang) + MinGW cross-compile PASS; 45 _Static_asserts (34 sizeof + 11 offsetof) lock the -mno-ms-bitfields N64 layout; negative control confirms non-vacuous. Closes FID-0035; first half of FID-0036 (converter risk-case union/pair-stride offsets locked)."
    }
  ]
}
